_mol2grid.cpython-38-x86_64-linux-gnu.so
mol2grid/main.py
mol2grid/__init__.py
mol2grid/utils.py
mol2grid/data/vdw.dat
mol2grid/data/catalog.dat
mol2grid-0.1.4.dist-info/RECORD
mol2grid-0.1.4.dist-info/METADATA
mol2grid-0.1.4.dist-info/top_level.txt
mol2grid-0.1.4.dist-info/WHEEL
mol2grid-0.1.4.dist-info/LICENSE
mol2grid-0.1.4.dist-info/entry_points.txt
mol2grid.libs/libgomp-f7e03b3e.so.1.0.0
