Metadata-Version: 2.1
Name: mol2grid
Version: 0.1.4
Summary: Python package to insert a ligand in a 3D grid, created based         on its respective receptor, considering each atom type as an integer
Home-page: https://github.com/LBC-LNBio/mol2grid
Author: João Victor da Silva Guerra
Author-email: jvsguerra@gmail.com
License: UNKNOWN
Project-URL: Source, https://github.com/LBC-LNBio/mol2grid/
Project-URL: Issues, https://github.com/LBC-LNBio/mol2grid/issues
Keywords: structural biology,proteins
Platform: UNKNOWN
Classifier: Development Status :: 3 - Alpha
Classifier: Intended Audience :: Science/Research
Classifier: Topic :: Scientific/Engineering :: Bio-Informatics
Classifier: Topic :: Scientific/Engineering :: Chemistry
Classifier: License :: OSI Approved :: GNU General Public License v3 (GPLv3)
Classifier: Programming Language :: Python :: 3
Classifier: Programming Language :: Python :: 3.7
Classifier: Programming Language :: Python :: 3.8
Classifier: Programming Language :: Python :: 3.9
Classifier: Programming Language :: Python :: 3 :: Only
Requires-Python: >=3.7, <4
Requires-Dist: toml (>=0.10.2)
Requires-Dist: numpy (>=1.20.3)
